schemdule/extensions/simplegui/__init__.py
schemdule/extensions/simplegui/__reg__.py
schemdule_extensions_simplegui-0.1.0.dist-info/METADATA
schemdule_extensions_simplegui-0.1.0.dist-info/WHEEL
schemdule_extensions_simplegui-0.1.0.dist-info/top_level.txt
schemdule_extensions_simplegui-0.1.0.dist-info/RECORD
